chull.py
chull-1.0.1.dist-info/LICENSE
chull-1.0.1.dist-info/METADATA
chull-1.0.1.dist-info/WHEEL
chull-1.0.1.dist-info/top_level.txt
chull-1.0.1.dist-info/RECORD
